llama_index/program/guidance/__init__.py
llama_index/program/guidance/base.py
llama_index/program/guidance/utils.py
llama_index_program_guidance-0.4.1.dist-info/METADATA
llama_index_program_guidance-0.4.1.dist-info/WHEEL
llama_index_program_guidance-0.4.1.dist-info/licenses/LICENSE
llama_index_program_guidance-0.4.1.dist-info/RECORD
