Metadata-Version: 2.4
Name: llama-index-program-guidance
Version: 0.4.1
Summary: llama-index program guidance integration
Author-email: Your Name <you@example.com>
License-Expression: MIT
License-File: LICENSE
Requires-Python: <4.0,>=3.9
Requires-Dist: guidance<0.2,>=0.1.16
Requires-Dist: llama-index-core<0.15,>=0.13.0
